nameko_http/__init__.py
nameko_http/constants.py
nameko_http/exceptions.py
nameko_http/http_api.py
nameko_http/server.py
nameko_http/utils.py
nameko_http-0.1.7.dist-info/METADATA
nameko_http-0.1.7.dist-info/WHEEL
nameko_http-0.1.7.dist-info/top_level.txt
nameko_http-0.1.7.dist-info/RECORD
