Metadata-Version: 2.1
Name: nameko-http
Version: 0.1.7
Summary: Http utilities for Nameko built-in HTTP extension
Home-page: https://github.com/tyler46/nameko_http
Author: Spyros Markopoulos
Author-email: mail.doctor46@gmail.com
License: UNKNOWN
Keywords: nameko_http
Platform: UNKNOWN
Classifier: Programming Language :: Python
Classifier: Intended Audience :: Developers
Classifier: Natural Language :: English
Classifier: Programming Language :: Python :: 2
Classifier: Programming Language :: Python :: 2.7
Classifier: Programming Language :: Python :: 3
Classifier: Programming Language :: Python :: 3.5
Classifier: Programming Language :: Python :: 3.6
Classifier: Programming Language :: Python :: 3.7
Requires-Dist: nameko (>=2.12.0)
Requires-Dist: python-mimeparse (>=1.6.0)
Provides-Extra: dev
Requires-Dist: pip (==18.1); extra == 'dev'
Requires-Dist: bumpversion (==0.5.3); extra == 'dev'
Requires-Dist: wheel (==0.32.2); extra == 'dev'
Requires-Dist: watchdog (==0.9.0); extra == 'dev'
Requires-Dist: flake8 (==3.5.0); extra == 'dev'
Requires-Dist: pylint (>=1.9.3); extra == 'dev'
Requires-Dist: tox (==3.5.2); extra == 'dev'
Requires-Dist: coverage (==4.5.1); extra == 'dev'
Requires-Dist: twine (==1.12.1); extra == 'dev'
